fileseek/__init__.py
fileseek/__main__.py
fileseek/cli/__init__.py
fileseek/cli/ascii_art.py
fileseek/cli/cli.py
fileseek/cli/ui_helpers.py
fileseek/core/__init__.py
fileseek/core/archivist.py
fileseek/core/config.py
fileseek/core/search_service.py
fileseek/core/system_deps.py
fileseek/pipeline/__init__.py
fileseek/pipeline/embedding_module.py
fileseek/pipeline/file_detector.py
fileseek/pipeline/ocr_module.py
fileseek/pipeline/pipeline.py
fileseek/storage/__init__.py
fileseek/storage/db_manager.py
fileseek/storage/vector_store.py
fileseek/vectors/__init__.py
fileseek/watchers/__init__.py
fileseek/watchers/watchers.py
fileseek-0.1.3.dist-info/LICENSE
fileseek-0.1.3.dist-info/METADATA
fileseek-0.1.3.dist-info/WHEEL
fileseek-0.1.3.dist-info/entry_points.txt
fileseek-0.1.3.dist-info/top_level.txt
fileseek-0.1.3.dist-info/RECORD
