Metadata-Version: 2.2
Name: fileseek
Version: 0.1.3
Summary: FileSeek – AI-Powered Local Document Archive&Search
Author-email: TangSheng <tangsheng001018@gmail.com>
License: MIT License
Keywords: document-management,semantic-search,vector-search,ocr,document-processing,file-monitoring,text-extraction,pdf-processing,local-search,offline-search,document-indexing,file-archival,text-analysis,document-similarity
Requires-Python: >=3.11
License-File: LICENSE
Requires-Dist: faiss-cpu>=1.7.4
Requires-Dist: chromadb>=0.4.22
Requires-Dist: numpy>=1.24.0
Requires-Dist: sentence-transformers>=2.2.0
Requires-Dist: torch>=2.0.0
Requires-Dist: tqdm>=4.65.0
Requires-Dist: python-magic>=0.4.27
Requires-Dist: chardet>=4.0.0
Requires-Dist: pdfplumber>=0.7.4
Requires-Dist: pytesseract>=0.3.10
Requires-Dist: pdf2image>=1.16.3
Requires-Dist: Pillow>=9.5.0
Requires-Dist: opencv-python>=4.8.0
Requires-Dist: rich>=13.3.5
Requires-Dist: click>=8.1.3
Requires-Dist: watchdog>=2.1.9
Requires-Dist: protobuf<4.0.0,>=3.12.0
Requires-Dist: openpyxl>=3.1.0
Requires-Dist: xlrd>=2.0.1
Requires-Dist: python-docx>=0.8.11
